README.md
setup.py
sterra/SterraException.py
sterra/__init__.py
sterra/__main__.py
sterra/_logo_.py
sterra/_outputs_.py
sterra/_sterrage_.py
sterra/_userAgents_.py
sterra/comparerra.py
sterra/core.py
sterra/exterra.py
sterra/filerra.py
sterra/histerra.py
sterra/stanalysis.py
sterra/stegram.py
sterra/sterools.py
sterratest.egg-info/PKG-INFO
sterratest.egg-info/SOURCES.txt
sterratest.egg-info/dependency_links.txt
sterratest.egg-info/entry_points.txt
sterratest.egg-info/requires.txt
sterratest.egg-info/top_level.txt