Metadata-Version: 2.1
Name: sterratest
Version: 4.1
Summary: A SOCMINT tool to analyse instagram followers|following of a target, and get informations from it.
Home-page: https://github.com/novitae/sterraxcyl
Author: novitae
License: GNU General Public License v3 (GPLv3)
Platform: UNKNOWN
Classifier: Programming Language :: Python :: 3.9
